Metadata-Version: 2.1
Name: auto-subtitle
Version: 1.0.1
Summary: Automatically generate and embed subtitles into your videos
Author: Miguel Piedrafita
License-File: LICENSE
